fastgeotoolkit-0.1.7.dist-info/METADATA
fastgeotoolkit-0.1.7.dist-info/WHEEL
fastgeotoolkit/__init__.py
fastgeotoolkit/_fastgeotoolkit.cpython-38-x86_64-linux-gnu.so
fastgeotoolkit/types.py
fastgeotoolkit/utils.py
fastgeotoolkit-0.1.7.dist-info/RECORD
