Metadata-Version: 2.4
Name: fastgeotoolkit
Version: 0.1.7
Classifier: Development Status :: 4 - Beta
Classifier: Intended Audience :: Developers
Classifier: Intended Audience :: Science/Research
Classifier: License :: OSI Approved :: MIT License
Classifier: Operating System :: OS Independent
Classifier: Programming Language :: Python :: 3
Classifier: Programming Language :: Python :: 3.8
Classifier: Programming Language :: Python :: 3.9
Classifier: Programming Language :: Python :: 3.10
Classifier: Programming Language :: Python :: 3.11
Classifier: Programming Language :: Python :: 3.12
Classifier: Programming Language :: Rust
Classifier: Topic :: Scientific/Engineering :: GIS
Classifier: Topic :: Software Development :: Libraries :: Python Modules
Classifier: Typing :: Typed
Requires-Dist: numpy>=1.20.0
Requires-Dist: typing-extensions>=4.0.0 ; python_full_version < '3.11'
Requires-Dist: pytest>=7.0.0 ; extra == 'dev'
Requires-Dist: pytest-cov>=4.0.0 ; extra == 'dev'
Requires-Dist: black>=22.0.0 ; extra == 'dev'
Requires-Dist: isort>=5.10.0 ; extra == 'dev'
Requires-Dist: mypy>=1.0.0 ; extra == 'dev'
Requires-Dist: flake8>=5.0.0 ; extra == 'dev'
Requires-Dist: sphinx>=5.0.0 ; extra == 'dev'
Requires-Dist: sphinx-rtd-theme>=1.0.0 ; extra == 'dev'
Requires-Dist: matplotlib>=3.5.0 ; extra == 'examples'
Requires-Dist: folium>=0.12.0 ; extra == 'examples'
Requires-Dist: geopandas>=0.10.0 ; extra == 'examples'
Requires-Dist: pandas>=1.3.0 ; extra == 'examples'
Requires-Dist: fastgeotoolkit[dev,examples] ; extra == 'all'
Provides-Extra: dev
Provides-Extra: examples
Provides-Extra: all
Summary: High-performance geospatial analysis framework
Keywords: gps,geospatial,trajectory,route-density,heatmap,gpx,fit,polyline,rust,performance
Author-email: a0a7 <contact@a0.ax>
License: MIT
Requires-Python: >=3.8
Project-URL: Bug Reports, https://github.com/a0a7/fastgeotoolkit/issues
Project-URL: Source, https://github.com/a0a7/fastgeotoolkit
Project-URL: Documentation, https://fastgeotoolkit.readthedocs.io
